rinoh_typeface_texgyretermes/GUST-FONT-LICENSE.txt
rinoh_typeface_texgyretermes/README-TeX-Gyre-Termes.txt
rinoh_typeface_texgyretermes/__init__.py
rinoh_typeface_texgyretermes/texgyretermes-bold.otf
rinoh_typeface_texgyretermes/texgyretermes-bolditalic.otf
rinoh_typeface_texgyretermes/texgyretermes-italic.otf
rinoh_typeface_texgyretermes/texgyretermes-regular.otf
rinoh_typeface_texgyretermes-0.1.1.dist-info/DESCRIPTION.rst
rinoh_typeface_texgyretermes-0.1.1.dist-info/METADATA
rinoh_typeface_texgyretermes-0.1.1.dist-info/RECORD
rinoh_typeface_texgyretermes-0.1.1.dist-info/WHEEL
rinoh_typeface_texgyretermes-0.1.1.dist-info/entry_points.txt
rinoh_typeface_texgyretermes-0.1.1.dist-info/metadata.json
rinoh_typeface_texgyretermes-0.1.1.dist-info/top_level.txt
